README.md
setup.cfg
setup.py
datalab/bigquery/__init__.py
datalab/bigquery/_api.py
datalab/bigquery/_csv_options.py
datalab/bigquery/_dataset.py
datalab/bigquery/_dialect.py
datalab/bigquery/_federated_table.py
datalab/bigquery/_job.py
datalab/bigquery/_parser.py
datalab/bigquery/_query.py
datalab/bigquery/_query_job.py
datalab/bigquery/_query_results_table.py
datalab/bigquery/_query_stats.py
datalab/bigquery/_sampling.py
datalab/bigquery/_schema.py
datalab/bigquery/_table.py
datalab/bigquery/_udf.py
datalab/bigquery/_utils.py
datalab/bigquery/_view.py
datalab/bigquery/commands/__init__.py
datalab/bigquery/commands/_bigquery.py
datalab/context/__init__.py
datalab/context/_api.py
datalab/context/_context.py
datalab/context/_project.py
datalab/context/_utils.py
datalab/context/commands/__init__.py
datalab/context/commands/_projects.py
datalab/data/__init__.py
datalab/data/_csv.py
datalab/data/_sql_module.py
datalab/data/_sql_statement.py
datalab/data/_utils.py
datalab/data/commands/__init__.py
datalab/data/commands/_sql.py
datalab/kernel/__init__.py
datalab/notebook/__init__.py
datalab/notebook/static/bigquery.css
datalab/notebook/static/bigquery.js
datalab/notebook/static/charting.css
datalab/notebook/static/charting.js
datalab/notebook/static/element.js
datalab/notebook/static/job.css
datalab/notebook/static/job.js
datalab/notebook/static/parcoords.js
datalab/notebook/static/style.js
datalab/notebook/static/visualization.js
datalab/notebook/static/extern/d3.parcoords.css
datalab/notebook/static/extern/d3.parcoords.js
datalab/notebook/static/extern/lantern-browser.html
datalab/notebook/static/extern/sylvester.js
datalab/stackdriver/__init__.py
datalab/stackdriver/commands/__init__.py
datalab/stackdriver/commands/_monitoring.py
datalab/stackdriver/monitoring/__init__.py
datalab/stackdriver/monitoring/_group.py
datalab/stackdriver/monitoring/_metric.py
datalab/stackdriver/monitoring/_query.py
datalab/stackdriver/monitoring/_query_metadata.py
rajivpb_datalab.egg-info/PKG-INFO
rajivpb_datalab.egg-info/SOURCES.txt
rajivpb_datalab.egg-info/dependency_links.txt
rajivpb_datalab.egg-info/namespace_packages.txt
rajivpb_datalab.egg-info/requires.txt
rajivpb_datalab.egg-info/top_level.txt