Metadata-Version: 1.1
Name: rajivpb-datalab
Version: 1.1.8
Summary: Google Cloud Datalab
Home-page: https://github.com/googledatalab/pydatalab
Author: Google
Author-email: google-cloud-datalab-feedback@googlegroups.com
License: Apache Software License
Download-URL: https://github.com/googledatalab/pydatalab/archive/v1.1.0.zip
Keywords: Google,GCP,GCS,bigquery
Platform: UNKNOWN
Classifier: Programming Language :: Python
Classifier: Programming Language :: Python :: 2
Classifier: Development Status :: 4 - Beta
Classifier: Environment :: Other Environment
Classifier: Intended Audience :: Developers
Classifier: License :: OSI Approved :: Apache Software License
Classifier: Operating System :: OS Independent
Classifier: Topic :: Software Development :: Libraries :: Python Modules
